airport/__init__.py
airport/_constants.py
airport/_datatypes.py
airport/_utils.py
airport_py-0.1.1.dist-info/LICENSE
airport_py-0.1.1.dist-info/METADATA
airport_py-0.1.1.dist-info/WHEEL
airport_py-0.1.1.dist-info/top_level.txt
airport_py-0.1.1.dist-info/RECORD
