Metadata-Version: 2.1
Name: airport-py
Version: 0.1.1
Summary: Mac OS X airport command result parser
Home-page: https://github.com/egemenyildiz/airport-py
Author: Egemen Yildiz
Author-email: egemenyildiz.e@gmail.com
License: UNKNOWN
Platform: UNKNOWN
Classifier: Programming Language :: Python :: 2 :: Only
Classifier: License :: OSI Approved :: MIT License
Classifier: Operating System :: MacOS :: MacOS X
Requires-Python: <=2.7.15
